pleiades/__init__.py
pleiades/_version.py
pleiades-1.0.dist-info/LICENSE.txt
pleiades-1.0.dist-info/METADATA
pleiades-1.0.dist-info/WHEEL
pleiades-1.0.dist-info/top_level.txt
pleiades-1.0.dist-info/RECORD
