Metadata-Version: 2.1
Name: pleiades
Version: 1.0
Summary: Pleiades: Metapackage for Reconstruction, Calibration, and Analysis of Rule-Based Models
Home-page: https://github.com/glucksfall/pleiades
Author: Rodrigo Santibáñez
Author-email: glucksfall@users.noreply.github.com
License: GPLv3+
Project-URL: Manual, https://pleiades.readthedocs.io
Project-URL: Bug Reports, https://github.com/glucksfall/pleiades/issues
Project-URL: Source, https://github.com/glucksfall/pleiades
Keywords: systems biology,stochastic modeling,parameter analysis
Platform: UNKNOWN
Classifier: Development Status :: 5 - Production/Stable
Classifier: Intended Audience :: Science/Research
Classifier: Topic :: Scientific/Engineering
Classifier: License :: OSI Approved :: GNU General Public License v3 or later (GPLv3+)
Classifier: Programming Language :: Python :: 3.6
Classifier: Programming Language :: Python :: 3.7
Classifier: Environment :: Console
Classifier: Operating System :: Unix
Requires-Python: >=3.0
Requires-Dist: atlas-rbm
Requires-Dist: pleione
Requires-Dist: alcyone
Requires-Dist: sterope
